yt/__init__.py
yt/formula/__init__.py
yt/formula/node.py
yt/formula/node_tests.py
yt.formula.node-0.0.4.dist-info/DESCRIPTION.rst
yt.formula.node-0.0.4.dist-info/METADATA
yt.formula.node-0.0.4.dist-info/RECORD
yt.formula.node-0.0.4.dist-info/WHEEL
yt.formula.node-0.0.4.dist-info/metadata.json
yt.formula.node-0.0.4.dist-info/top_level.txt
